fuxi_kit/__init__.py
fuxi_kit/__main__.py
fuxi_kit-0.1.9.dist-info/LICENSE
fuxi_kit-0.1.9.dist-info/METADATA
fuxi_kit-0.1.9.dist-info/WHEEL
fuxi_kit-0.1.9.dist-info/top_level.txt
fuxi_kit-0.1.9.dist-info/RECORD
