Metadata-Version: 2.1
Name: fuxi-kit
Version: 0.1.9
Summary: A kit for fuxi web.
Author: 623
License: MIT License
Project-URL: Repository, https://github.com/fuxiproject/fuxi-kit-py.git
Keywords: OpenVPN,web
Classifier: Development Status :: 4 - Beta
Classifier: Intended Audience :: Developers
Classifier: Topic :: Software Development :: Libraries :: Python Modules
Classifier: License :: OSI Approved :: MIT License
Classifier: Programming Language :: Python :: 3 :: Only
Classifier: Programming Language :: Python :: 3.8
Classifier: Programming Language :: Python :: 3.9
Classifier: Programming Language :: Python :: 3.10
Classifier: Programming Language :: Python :: 3.11
Classifier: Programming Language :: Python :: 3.12
Requires-Python: >=3.8
License-File: LICENSE
Requires-Dist: aiohttp ==3.9.5
Requires-Dist: PyYAML ==6.0.1
Provides-Extra: dev
Requires-Dist: black ; extra == 'dev'
Requires-Dist: pylint ; extra == 'dev'
